{
    "id": "991ecef2584e47f0b3930ae97cd99c7e",
    "title": "Vegetables",
    "questions": [
        {
            "id": "346a7c8a6f074a5784eb3cea3b251d04",
            "text": "Vegetables are very good for you.",
            "items": [
                "Vegetables",
                "are",
                "very",
                "good",
                "for",
                "you."
            ]
        },
        {
            "id": "22db980f4a454b8f9bae4f0bb7a680ec",
            "text": "They say that you should have three servings of vegetables every day.",
            "items": [
                "They",
                "say",
                "that",
                "you",
                "should",
                "have",
                [
                    "three",
                    "3"
                ],
                "servings",
                "of",
                "vegetables",
                "every",
                "day."
            ]
        },
        {
            "id": "3c077154201f4c06873a3e7b77b43e8b",
            "text": "I like green peas. Peas come in pods.",
            "items": [
                "I",
                "like",
                "green",
                "peas.",
                "Peas",
                "come",
                "in",
                "pods."
            ]
        },
        {
            "id": "a72a201ea59949d8a91a0cf5c6c55f0a",
            "text": "I also like snow peas. You eat the pods on the snow peas.",
            "items": [
                "I",
                "also",
                "like",
                "snow",
                "peas.",
                "You",
                "eat",
                "the",
                "pods",
                "on",
                "the",
                "snow",
                "peas."
            ]
        },
        {
            "id": "05a2ebdab03b409b87225f057f09e8b2",
            "text": "I like corn when it is on the cob.",
            "items": [
                "I",
                "like",
                "corn",
                "when",
                "it",
                "is",
                "on",
                "the",
                "cob."
            ]
        },
        {
            "id": "9d737557164b424f99e1e49535b5d7e0",
            "text": "Carrots are good to eat raw.",
            "items": [
                "Carrots",
                "are",
                "good",
                "to",
                "eat",
                "raw."
            ]
        },
        {
            "id": "418adcebf93b4d56ab973ea26ff0471b",
            "text": "Beans are good for you.",
            "items": [
                "Beans",
                "are",
                "good",
                "for",
                "you."
            ]
        },
        {
            "id": "abf8866d00eb479f9de83ac76959ddbb",
            "text": "There are many different types of beans.",
            "items": [
                "There",
                "are",
                "many",
                "different",
                "types",
                "of",
                "beans."
            ]
        },
        {
            "id": "a73a4a649d2e4f5e9001144d735e083e",
            "text": "There are string beans, kidney beans, baked beans and lots of other types of beans.",
            "items": [
                "There",
                "are",
                "string",
                "beans,",
                "kidney",
                "beans,",
                "baked",
                "beans",
                "and",
                "lots",
                "of",
                "other",
                "types",
                "of",
                "beans."
            ]
        },
        {
            "id": "1d1a9a6eb2cc4e9ab677474ddfb72b31",
            "text": "Some people don't like green vegetables like broccoli and Brussels sprouts.",
            "items": [
                "Some",
                "people",
                "don't",
                "like",
                "green",
                "vegetables",
                "like",
                "broccoli",
                "and",
                "Brussels",
                "sprouts."
            ]
        },
        {
            "id": "10ec46a076ff46e6ae79fb4186f95a7a",
            "text": "I like broccoli and Brussels sprouts.",
            "items": [
                "I",
                "like",
                "broccoli",
                "and",
                "Brussels",
                "sprouts."
            ]
        },
        {
            "id": "0538f68829124d24ba888d81de0ec74d",
            "text": "You can make a salad and put lots of different vegetables into the salad.",
            "items": [
                "You",
                "can",
                "make",
                "a",
                "salad",
                "and",
                "put",
                "lots",
                "of",
                "different",
                "vegetables",
                "into",
                "the",
                "salad."
            ]
        },
        {
            "id": "92760ce8a69c4c219935522b65199e22",
            "text": "In my salads, I like lettuce, tomatoes, celery,",
            "items": [
                "In",
                "my",
                "salads,",
                "I",
                "like",
                "lettuce,",
                "tomatoes,",
                "celery,"
            ]
        },
        {
            "id": "cbb6d2ec88bb41348463ca7a04e5cc86",
            "text": "cucumber, radishes, cauliflower and spring onions.",
            "items": [
                "cucumber,",
                "radishes,",
                "cauliflower",
                "and",
                "spring",
                "onions."
            ]
        },
        {
            "id": "111e885f9b9e4a6984fe7a681909a7f4",
            "text": "I try to have a salad with dressing on it every day.",
            "items": [
                "I",
                "try",
                "to",
                "have",
                "a",
                "salad",
                "with",
                "dressing",
                "on",
                "it",
                "every",
                "day."
            ]
        },
        {
            "id": "33ba23e568984ae1b9f2c8a6cd76853e",
            "text": "My dad likes root vegetables like beets and parsnips.",
            "items": [
                "My",
                "dad",
                "likes",
                "root",
                "vegetables",
                "like",
                "beets",
                "and",
                "parsnips."
            ]
        },
        {
            "id": "445d3fa3e05b44b7b36e7b373ed14a19",
            "text": "My brother will only eat potatoes.",
            "items": [
                "My",
                "brother",
                "will",
                "only",
                "eat",
                "potatoes."
            ]
        },
        {
            "id": "8b4e43a38cd24947b91014fb5d8821a6",
            "text": "He likes his potatoes baked.",
            "items": [
                "He",
                "likes",
                "his",
                "potatoes",
                "baked."
            ]
        },
        {
            "id": "84fdbaf1c34947488fcfe6072c91987e",
            "text": "My mother likes to buy her vegetables at the market.",
            "items": [
                "My",
                "mother",
                "likes",
                "to",
                "buy",
                "her",
                "vegetables",
                "at",
                "the",
                "market."
            ]
        },
        {
            "id": "32e489e5aceb461b8dc9c59499c385fb",
            "text": "She says they are fresher there.",
            "items": [
                "She",
                "says",
                "they",
                "are",
                "fresher",
                "there."
            ]
        },
        {
            "id": "a4711b7172f647279c62adc5ec020fc3",
            "text": "My mother buys a lot of onions.",
            "items": [
                "My",
                "mother",
                "buys",
                "a",
                "lot",
                "of",
                "onions."
            ]
        },
        {
            "id": "7ef118ba08694558b06ec1f7720d6373",
            "text": "She puts onions in almost all the meals that she cooks.",
            "items": [
                "She",
                "puts",
                "onions",
                "in",
                "almost",
                "all",
                "the",
                "meals",
                "that",
                "she",
                "cooks."
            ]
        },
        {
            "id": "a7043df3e418406da05ae9919ae8da0d",
            "text": "Some children won't eat their vegetables.",
            "items": [
                "Some",
                "children",
                "won't",
                "eat",
                "their",
                "vegetables."
            ]
        },
        {
            "id": "67a411e4afb94309a4b4c9fb4b95d062",
            "text": "I didn't like some vegetables at first,",
            "items": [
                "I",
                "didn't",
                "like",
                "some",
                "vegetables",
                "at",
                [
                    "first,",
                    "1st"
                ]
            ]
        },
        {
            "id": "eff05ea249924c94b4d8cbd1496a1ec9",
            "text": "but I have become used to them.",
            "items": [
                "but",
                "I",
                "have",
                "become",
                "used",
                "to",
                "them."
            ]
        },
        {
            "id": "1c2b7eef16b54ba1a75720d00dd33d98",
            "text": "I like having vegetables with my meals.",
            "items": [
                "I",
                "like",
                "having",
                "vegetables",
                "with",
                "my",
                "meals."
            ]
        }
    ]
}